[
    {
        "url": "https://juejin.cn/post/7542164564230979630",
        "desc": "在前端打包工具（如Vite、Webpack等）的配置中，`base`、`publicPath`和`publicDir`是与资源路径和静态文件处理相关的重要配置项。",
        "time": "2025-08-25 08:20:04",
        "timestamp": 1756110004000,
        "image": "",
        "title": "打包工具配置base、publicPath字段的作用和区别",
        "articleId": "7542164564230979630",
        "website": "juejin"
    },
    {
        "url": "https://juejin.cn/post/7541714394017546249",
        "desc": "类 单一职责原则 单一职责原则是面向对象设计原则，为了降低复杂性，耦合性和提高可维护性。一个类只承担一项职责与功能，承担的功能更多会让可读性降低。 实现单一职责的原则 1.识别和分离职责 识别类中是否",
        "time": "2025-08-25 03:16:27",
        "timestamp": 1756091787000,
        "image": "",
        "title": "Clean Code JavaScript小记（二）",
        "articleId": "7541714394017546249",
        "website": "juejin"
    },
    {
        "url": "https://juejin.cn/post/7541334950663602212",
        "desc": "在当今互联网应用规模不断扩大、功能日益复杂的背景下，传统的单体架构已经难以满足快速迭代和团队协作的需求。微前端架构应运而生，它允许将一个庞大的前端应用拆分成多个独立开发、独立部署的小型应用",
        "time": "2025-08-25 02:22:43",
        "timestamp": 1756088563000,
        "image": "https://p3-xtjj-sign.byteimg.com/tos-cn-i-73owjymdk6/ca9f47f1ecda456aa95b7f836636cd6a~tplv-73owjymdk6-jj-mark-v1:0:0:0:0:5o6Y6YeR5oqA5pyv56S-5Yy6IEAg5YmN56uv5Zi_6LW3:q75.awebp?rk3s=f64ab15b&x-expires=1756717953&x-signature=4CGcoQv3WzVo88MRVPxRe02GNKw%3D",
        "title": "微服务架构的利器：qiankun框架深度剖析与实战指南",
        "articleId": "7541334950663602212",
        "website": "juejin"
    },
    {
        "url": "https://juejin.cn/post/7541420187122483209",
        "desc": "一、双向绑定 二、指令系统 三、组件 生命周期 通信 选项，组合式 虚拟Dom 四、mixin 五、keep alive 缓存机制 <keep-alive> 会将包裹的组件实例缓存到一个内部对象（通常",
        "time": "2025-08-25 02:06:45",
        "timestamp": 1756087605000,
        "image": "",
        "title": "Vue知识总结",
        "articleId": "7541420187122483209",
        "website": "juejin"
    },
    {
        "url": "https://juejin.cn/post/7541339617490927659",
        "desc": "🌰栗子前端技术周刊第 95 期 (2025.08.18 - 2025.08.24)：浏览前端一周最新消息，学习国内外优秀文章视频，让我们保持对前端的好奇心。 📰 技术资讯 Next.js 15.5：N",
        "time": "2025-08-25 00:47:14",
        "timestamp": 1756082834000,
        "image": "https://p3-xtjj-sign.byteimg.com/tos-cn-i-73owjymdk6/dd5f3510953f4567946873ee3a3a9556~tplv-73owjymdk6-jj-mark-v1:0:0:0:0:5o6Y6YeR5oqA5pyv56S-5Yy6IEAg5pmT5b6X6L-36Lev5LqG:q75.awebp?rk3s=f64ab15b&x-expires=1756717953&x-signature=Js96QbVh2KzkLreLE9mdB7Chovg%3D",
        "title": "栗子前端技术周刊第 95 期 - Next.js 15.5、Rslint、2025 年 CSS 现状报告...",
        "articleId": "7541339617490927659",
        "website": "juejin"
    },
    {
        "url": "https://juejin.cn/post/7541339617490878507",
        "desc": "作为一个效率至上的开发者，我一直习惯用油猴脚本来扩展网页功能，提升日常开发效率。这也是我写下《油猴脚本实战指南》这本小册的初衷。 直到有一天，我突然想到：能不能把油猴脚本直接“打包”成原生谷歌插件？这",
        "time": "2025-08-25 00:32:48",
        "timestamp": 1756081968000,
        "image": "https://p3-xtjj-sign.byteimg.com/tos-cn-i-73owjymdk6/2f6be3491f9e4563b969666dba775591~tplv-73owjymdk6-jj-mark-v1:0:0:0:0:5o6Y6YeR5oqA5pyv56S-5Yy6IEAg55-z5bCP55-zT3J6:q75.awebp?rk3s=f64ab15b&x-expires=1756717953&x-signature=65IJrW2S5ZCcQwWXwOLjzflrRuQ%3D",
        "title": "使用Trae将油猴脚本打包成谷歌插件",
        "articleId": "7541339617490878507",
        "website": "juejin"
    },
    {
        "url": "https://juejin.cn/post/7541801054180261914",
        "desc": "Shorebird 联合 Appwrite 实现更新逻辑？ 距离上一篇关于 Flutter 热更新的文章已经快要两年，项目从 1.0 到目前 2.0 开发完毕准备上线，这期间大概两年时间我竟然才想起来",
        "time": "2025-08-24 08:25:55",
        "timestamp": 1756023955000,
        "image": "https://p3-xtjj-sign.byteimg.com/tos-cn-i-73owjymdk6/a2dd2b56bdd04320b54d4c046c916e34~tplv-73owjymdk6-jj-mark-v1:0:0:0:0:5o6Y6YeR5oqA5pyv56S-5Yy6IEAg5ZCb6LWP:q75.awebp?rk3s=f64ab15b&x-expires=1756717953&x-signature=vWTIfsnNEwVgBUBtaWyOKmbd6jg%3D",
        "title": "Petrel(雨燕) 新一代 Flutter Web 热更新框架.",
        "articleId": "7541801054180261914",
        "website": "juejin"
    },
    {
        "url": "https://juejin.cn/post/7541226780641280009",
        "desc": "虚拟列表：如何高效显示大量数据 当一个网页需要展示大量数据时，比如一个有1万条记录的列表，如果直接将所有数据渲染成DOM元素，页面会变得非常慢，甚至卡死。这是因为浏览器需要处理大量的节点，占用大量内存",
        "time": "2025-08-23 08:58:23",
        "timestamp": 1755939503000,
        "image": "",
        "title": "虚拟列表：怎么显示大量数据不卡",
        "articleId": "7541226780641280009",
        "website": "juejin"
    },
    {
        "url": "https://juejin.cn/post/7538720615357808690",
        "desc": "前言 Node.js v24.6.0 发布了，让我们一起来看看这些朴实却强大的变化！ 往期精彩推荐 🔥🔥🔥 原来在字节写代码就是这么朴实无华！🔥🔥🔥 🚀🚀🚀恭喜 Rolldown 获得 JS 开源奖年",
        "time": "2025-08-17 07:53:32",
        "timestamp": 1755417212000,
        "image": "https://p3-xtjj-sign.byteimg.com/tos-cn-i-73owjymdk6/bfffab05ef3343d3a6570f6fd567af05~tplv-73owjymdk6-jj-mark-v1:0:0:0:0:5o6Y6YeR5oqA5pyv56S-5Yy6IEAg6JCM6JCM5ZOS6I2J5aS05bCG5Yab:q75.awebp?rk3s=f64ab15b&x-expires=1756717953&x-signature=rdjb%2Fd9sksA6POIVrKPHYAQVoLI%3D",
        "title": "Node.js v24.6.0 新功能速览 🚀🚀🚀",
        "articleId": "7538720615357808690",
        "website": "juejin"
    },
    {
        "url": "https://juejin.cn/post/7536228418829959177",
        "desc": "时隔一年，我终于带着新的思考成果回来了。回归原生 JavaScript 的纯净力量，性能、体验与持续精进。",
        "time": "2025-08-10 11:29:41",
        "timestamp": 1754825381000,
        "image": "https://p3-xtjj-sign.byteimg.com/tos-cn-i-73owjymdk6/7ef8ff8adc3c4a62aa1c5d77645f7447~tplv-73owjymdk6-jj-mark-v1:0:0:0:0:5o6Y6YeR5oqA5pyv56S-5Yy6IEAgVmFt55qE6YeR6LGG5LmL6Lev:q75.awebp?rk3s=f64ab15b&x-expires=1756717953&x-signature=LH1azTqIa%2Bc1iHq4GnWY4BoOnOI%3D",
        "title": "🔥 1.30 分！我的 JS 库 Mettle.js 杀入全球性能榜，紧追 Vue",
        "articleId": "7536228418829959177",
        "website": "juejin"
    },
    {
        "url": "https://juejin.cn/post/7502268562096160768",
        "desc": "SSE接入的具体落地有几种方案 ## 1. EventSource 实现接入 EventSource 是一个 `Web API`，**是浏览器提供的原生对象，专门用于处理 SSE**。使用简单，对",
        "time": "2025-08-01 02:10:02",
        "timestamp": 1754014202000,
        "image": "",
        "title": "做大模型应用的你们，真的懂SSE方案吗？",
        "articleId": "7502268562096160768",
        "website": "juejin"
    },
    {
        "url": "https://juejin.cn/post/7503716790615228452",
        "desc": "那个让我熬夜到两点的数字滚动效果，原来是这样实现的！ 缘起：被某度首页种草的计数器 昨晚刷着手机，突然看到某度首页那个酷炫的AI调用次数计数器——数字像滚筒洗衣机一样唰唰滚动，最后稳稳停在目标数值。",
        "time": "2025-07-22 08:46:25",
        "timestamp": 1753173985000,
        "image": "https://p3-xtjj-sign.byteimg.com/tos-cn-i-73owjymdk6/7c7d2c426f2347b4b80b86eb32ece87a~tplv-73owjymdk6-jj-mark-v1:0:0:0:0:5o6Y6YeR5oqA5pyv56S-5Yy6IEAg5LiJ5Liq5pyoYmFzZQ==:q75.awebp?rk3s=f64ab15b&x-expires=1756717953&x-signature=ShgiAM64XPcA9nz%2Fg0SY%2F8ol%2BIM%3D",
        "title": "那个让我熬夜到两点的数字滚动效果，原来是这样实现的！",
        "articleId": "7503716790615228452",
        "website": "juejin"
    },
    {
        "url": "https://juejin.cn/post/7504567245266305024",
        "desc": "rengar-admin —— 现代轻量的 Vue3+TS 后台管理模板 项目简介 rengar-admin 是一款基于 Naive UI 开发的 Vue3+TypeScript 后台管理模板，有点特",
        "time": "2025-07-09 07:16:41",
        "timestamp": 1752045401000,
        "image": "https://p3-xtjj-sign.byteimg.com/tos-cn-i-73owjymdk6/f9e33fa34c7942d9a01d1451b62a127f~tplv-73owjymdk6-jj-mark-v1:0:0:0:0:5o6Y6YeR5oqA5pyv56S-5Yy6IEAgYXNodWljb2Rlcg==:q75.awebp?rk3s=f64ab15b&x-expires=1756717953&x-signature=W4CVwQBNUlzCpUt7aMGw5A7ztu4%3D",
        "title": "rengar-admin —— 轻量、现代的 Vue3+TS 后台管理模板",
        "articleId": "7504567245266305024",
        "website": "juejin"
    },
    {
        "url": "https://juejin.cn/post/7518475441171267599",
        "desc": "背景 最近在工作中，接手了个 vue2 的老项目，面对上百个文件项目，而且有一大部分的一个 vue 文件有上万行代码，甚至有几万行代码，让整个前端团队的人都叫苦连连；于是团队决定对这个项目进行一定的升",
        "time": "2025-06-23 02:19:09",
        "timestamp": 1750645149000,
        "image": "",
        "title": "对于vue2的老项目，我们应该怎么做无痛的优化和升级",
        "articleId": "7518475441171267599",
        "website": "juejin"
    },
    {
        "url": "https://juejin.cn/post/7518275819530616859",
        "desc": "项目级组件封装指南 相信在开发过程中经常会出现这种情况，需求要求的内容已经开发好了，但是开发过程中制作了某个组件看起来有一定的通用潜力。 这时候你就陷入了纠结，一方面是把这个组件抽离出来能够提升后续相",
        "time": "2025-06-23 02:04:18",
        "timestamp": 1750644258000,
        "image": "https://p3-xtjj-sign.byteimg.com/tos-cn-i-73owjymdk6/6adab128998a4f8e9407b15438fbfaf4~tplv-73owjymdk6-jj-mark-v1:0:0:0:0:5o6Y6YeR5oqA5pyv56S-5Yy6IEAgUkppYXpoZW4=:q75.awebp?rk3s=f64ab15b&x-expires=1756717953&x-signature=%2BibrQ7JGOqAv7rs21jbDApjg5wg%3D",
        "title": "项目级组件封装指南",
        "articleId": "7518275819530616859",
        "website": "juejin"
    },
    {
        "url": "https://juejin.cn/post/7512058418623971343",
        "desc": "前言 我偶然间发现一个宝藏网站，http://aicut.online 是一款基于本地AI实现的背景移除工具。 我研究了一下，发现他是使用了u2net模型 + onnxruntime-web实现的本地",
        "time": "2025-06-06 06:32:05",
        "timestamp": 1749191525000,
        "image": "https://p3-xtjj-sign.byteimg.com/tos-cn-i-73owjymdk6/3034a776a607439da125937416375658~tplv-73owjymdk6-jj-mark-v1:0:0:0:0:5o6Y6YeR5oqA5pyv56S-5Yy6IEAg5oiR5piv5bCP5LiD5ZGm:q75.awebp?rk3s=f64ab15b&x-expires=1756717953&x-signature=72yt3j7y2Pno5Xgl6oa41dveGN4%3D",
        "title": "😧纳尼？前端也能做这么复杂的事情了？",
        "articleId": "7512058418623971343",
        "website": "juejin"
    },
    {
        "url": "https://juejin.cn/post/7506546710207741962",
        "desc": "作为前端开发者，我在学习ES6特性时，总被const的\"善变\"搞得一头雾水——为什么用const声明的数组还能push元素？为什么基本类型赋值就会报错？直到翻遍MDN文档、对着内存图反复推敲，才终于理",
        "time": "2025-05-26 03:29:37",
        "timestamp": 1748230177000,
        "image": "https://p3-xtjj-sign.byteimg.com/tos-cn-i-73owjymdk6/39b16e53461c49eb9182973624bb19ac~tplv-73owjymdk6-jj-mark-v1:0:0:0:0:5o6Y6YeR5oqA5pyv56S-5Yy6IEAg5rW35bqV54Gr5pe6:q75.awebp?rk3s=f64ab15b&x-expires=1756717953&x-signature=SOpsgTKB%2FEieB3g5Pxk3HCo7htk%3D",
        "title": "面试官最爱问的 const 问题：‘不可变’到底是值不变还是地址不变？一篇搞懂",
        "articleId": "7506546710207741962",
        "website": "juejin"
    },
    {
        "url": "https://juejin.cn/post/7504552218067959845",
        "desc": "通过本篇文章大家会学习到： 如何使用Recoil Recoil优势在哪？ 如何使用Recoil Recoil是开发的第三方库，所以我们想要用它首先就得把包下载下来 npm： yarn： 如需在组件中使",
        "time": "2025-05-16 02:40:08",
        "timestamp": 1747363208000,
        "image": "",
        "title": "🤭同事说Redux太恶心了，换了Recoil是真香🍰",
        "articleId": "7504552218067959845",
        "website": "juejin"
    },
    {
        "url": "https://juejin.cn/post/7503437639690649636",
        "desc": "我们一般创建一个vue3项目会从createApp或createSSRApp开始，createSSRApp是服务端渲染的入口，createApp是客户端渲染的入口。 1.createApp 、 cre",
        "time": "2025-05-15 07:15:04",
        "timestamp": 1747293304000,
        "image": "",
        "title": "vue3源码解析（一）",
        "articleId": "7503437639690649636",
        "website": "juejin"
    },
    {
        "url": "https://juejin.cn/post/7497804336568057895",
        "desc": "面试官冷冷一笑，盯着我手里的简历。 “你说你写过 React 项目？” “是的。” “那……受控组件和非受控组件，讲讲。” 我心头一震，表面淡定地微笑，脑子却飞快回想起那些我曾无数次敲下的 `v",
        "time": "2025-04-28 10:38:21",
        "timestamp": 1745836701000,
        "image": "https://p3-xtjj-sign.byteimg.com/tos-cn-i-73owjymdk6/5e2a6af5778545b9992451432c0518a6~tplv-73owjymdk6-jj-mark-v1:0:0:0:0:5o6Y6YeR5oqA5pyv56S-5Yy6IEAgSmlhbmdKaWFuZw==:q75.awebp?rk3s=f64ab15b&x-expires=1756717953&x-signature=ZT99%2BGG06tg0qtQ2IsBEKGP7Zc0%3D",
        "title": "🧠 面试官：受控组件都分不清？还敢说自己写过 React？",
        "articleId": "7497804336568057895",
        "website": "juejin"
    }
]